pyolcb/__init__.py
pyolcb/address.py
pyolcb/datagram.py
pyolcb/event.py
pyolcb/exceptions.py
pyolcb/interface.py
pyolcb/message.py
pyolcb/message_types.py
pyolcb/node.py
pyolcb/protocols.py
pyolcb/utilities.py
tests/__init__.py
tests/test_node.py
pyOLCB-0.1.0.dist-info/LICENSE
pyOLCB-0.1.0.dist-info/METADATA
pyOLCB-0.1.0.dist-info/WHEEL
pyOLCB-0.1.0.dist-info/top_level.txt
pyOLCB-0.1.0.dist-info/RECORD
