Metadata-Version: 2.1
Name: pyOLCB
Version: 0.1.0
Summary: An easy to use Python implementation of OpenLCB (LCC) protocols, designed to interface with both CAN and TCP/IP
Home-page: https://github.com/UncommonModels/pyOLCB
Author: ngpaladi
Author-email: pyOLCB@uncommonmodels.com
Classifier: Programming Language :: Python :: 3
Classifier: License :: OSI Approved :: Apache Software License
Classifier: Operating System :: OS Independent
Requires-Python: >3.10.8
License-File: LICENSE
Requires-Dist: python-can
